COPYING
MANIFEST.in
README
health_stock_view.xml
setup.py
./__init__.py
./health_stock.py
./health_stock_view.xml
./tryton.cfg
./doc/index.rst
./locale/ar.po
./locale/de.po
./locale/el.po
./locale/es.po
./locale/fr.po
./locale/it_IT.po
./locale/ja_JP.po
./locale/lo.po
./locale/pt_BR.po
./locale/zh_CN.po
./tests/__init__.py
./tests/test_health_stock.py
./view/ambulatory_care_form.xml
./view/create_prescription_stock_move.xml
./view/create_vaccination_stock_move.xml
./view/gnuhealth_ambulatory_care_medical_supplies_tree.xml
./view/gnuhealth_ambulatory_care_medicament_form.xml
./view/gnuhealth_ambulatory_care_medicament_tree.xml
./view/gnuhealth_ambulatory_care_vaccine_form.xml
./view/gnuhealth_ambulatory_care_vaccine_tree.xml
./view/gnuhealth_medicament_tree_stock.xml
./view/gnuhealth_patient_ambulatory_care_tree.xml
./view/gnuhealth_patient_rounding.xml
./view/gnuhealth_patient_rounding_tree.xml
./view/gnuhealth_rounding_medical_supply_tree.xml
./view/gnuhealth_rounding_medicament_form.xml
./view/gnuhealth_rounding_medicament_tree.xml
./view/gnuhealth_rounding_vaccine_form.xml
./view/gnuhealth_rounding_vaccine_tree.xml
./view/lot_form.xml
./view/lot_tree.xml
./view/move_form.xml
./view/move_tree.xml
./view/party_form.xml
./view/vaccination_form.xml
./wizard/__init__.py
./wizard/create_prescription_stock_move.xml
./wizard/create_vaccination_stock_move.xml
./wizard/wizard_create_prescription_stock_move.py
./wizard/wizard_create_vaccination_stock_move.py
locale/ar.po
locale/de.po
locale/el.po
locale/es.po
locale/fr.po
locale/it_IT.po
locale/ja_JP.po
locale/lo.po
locale/pt_BR.po
locale/zh_CN.po
trytond_health_stock.egg-info/PKG-INFO
trytond_health_stock.egg-info/SOURCES.txt
trytond_health_stock.egg-info/dependency_links.txt
trytond_health_stock.egg-info/entry_points.txt
trytond_health_stock.egg-info/not-zip-safe
trytond_health_stock.egg-info/requires.txt
trytond_health_stock.egg-info/top_level.txt
view/ambulatory_care_form.xml
view/create_prescription_stock_move.xml
view/create_vaccination_stock_move.xml
view/gnuhealth_ambulatory_care_medical_supplies_tree.xml
view/gnuhealth_ambulatory_care_medicament_form.xml
view/gnuhealth_ambulatory_care_medicament_tree.xml
view/gnuhealth_ambulatory_care_vaccine_form.xml
view/gnuhealth_ambulatory_care_vaccine_tree.xml
